freelance_tasks/__init__.py
freelance_tasks/base_user.html
freelance_tasks/habr.py
freelance_tasks/models.py
freelance_tasks-1.0.16.dist-info/METADATA
freelance_tasks-1.0.16.dist-info/WHEEL
freelance_tasks-1.0.16.dist-info/RECORD
