Metadata-Version: 2.1
Name: freelance_tasks
Version: 1.0.16
Summary: Parse freelance
Author: Skelesheit
Author-email: skelesheit@gmail.com
Requires-Python: >=3.8,<4.0
Classifier: Programming Language :: Python :: 3
Classifier: Programming Language :: Python :: 3.8
Classifier: Programming Language :: Python :: 3.9
Classifier: Programming Language :: Python :: 3.10
Classifier: Programming Language :: Python :: 3.11
Classifier: Programming Language :: Python :: 3.12
Classifier: Programming Language :: Python :: 3.13
Classifier: Programming Language :: Python :: 3 :: Only
Requires-Dist: beautifulsoup4 (>=4.12,<5.0)
Requires-Dist: lxml (>=5,<6)
Requires-Dist: pydantic (>=2,<3)
Requires-Dist: requests (>=2.32,<3.0)
